ETL_Infra/__init__.py
ETL_Infra/build_config_file.py
ETL_Infra/create_lab_reference_tests.py
ETL_Infra/define_signals.py
ETL_Infra/dict_utils.py
ETL_Infra/env.py
ETL_Infra/etl_loading_status.py
ETL_Infra/etl_process.py
ETL_Infra/logger.py
ETL_Infra/map_signals.py
ETL_Infra/plot_graph.py
ETL_Infra/process_signals.py
ETL_Infra/run_test_on_sig.py
ETL_Infra/test_signals.py
ETL_Infra/unit_conversions.py
ETL_Infra/data_fetcher/__init__.py
ETL_Infra/data_fetcher/db_fetcher.py
ETL_Infra/data_fetcher/files_fetcher.py
ETL_Infra/dicts/ATC/dict.defs_atc
ETL_Infra/dicts/ATC/dict.defs_atc_syn
ETL_Infra/dicts/ATC/dict.sets_atc
ETL_Infra/dicts/ICD10/dict.icd10
ETL_Infra/dicts/ICD10/dict.icd10pcs
ETL_Infra/dicts/ICD10/dict.set_icd10
ETL_Infra/dicts/ICD10/dict.set_icd10pcs
ETL_Infra/dicts/ICD10_TO_ICD9/dict.set_icd10_2_icd9
ETL_Infra/dicts/ICD10_TO_SNOMED/dict.icd10_additional_from_snomed
ETL_Infra/dicts/ICD10_TO_SNOMED/dict.sets_icd10_snomed
ETL_Infra/dicts/ICD9/dict.icd9dx
ETL_Infra/dicts/ICD9/dict.icd9sg
ETL_Infra/dicts/ICD9/dict.set_icd9dx
ETL_Infra/dicts/ICD9/dict.set_icd9sg
ETL_Infra/dicts/ICD9_TO_ICD10/dict.set_icd9_2_icd10
ETL_Infra/dicts/NDC/dict.atc_ndc_set
ETL_Infra/dicts/NDC/dict.ndc_defs
ETL_Infra/dicts/READCODES/dict.read_codes
ETL_Infra/dicts/READCODES_TO_ICD10/dict.rc_icd_set
ETL_Infra/dicts/RX/dict.sets_atc_rx
ETL_Infra/dicts/SNOMED_Condition/dict.defs_snomed
ETL_Infra/rep_signals/general.signals
ETL_Infra/rep_signals/lab_zero_value_allowed.txt
ETL_Infra/rep_signals/signals_prctile.cfg
ETL_Infra/rep_signals/unit_suggestions.cfg
ETL_Infra/tests/GENDER/test_values.py
ETL_Infra/tests/date/test_date.py
ETL_Infra/tests/demographic/test_not_null.py
ETL_Infra/tests/labs/test_lab_different_sources.py
ETL_Infra/tests/labs/test_lab_values.py
ETL_Infra/tests/labs/test_labs_units_conversion_values.py
ETL_Infra/tests/labs/test_non_nulls.py
ETL_Infra/tests/singleton/test_single.py
ETL_Infra/tests/smoking/test_not_null.py
ETL_Infra/tests/smoking/test_smoking.py
medpython_etl-1.0.3.dist-info/licenses/LICENCE
medpython_etl-1.0.3.dist-info/METADATA
medpython_etl-1.0.3.dist-info/WHEEL
medpython_etl-1.0.3.dist-info/top_level.txt
medpython_etl-1.0.3.dist-info/RECORD
